cwlformat/__init__.py
cwlformat/explode.py
cwlformat/formatter.py
cwlformat/keyorder.yml
cwlformat/version.py
cwlformat-2022.2.18.dist-info/LICENSE
cwlformat-2022.2.18.dist-info/METADATA
cwlformat-2022.2.18.dist-info/WHEEL
cwlformat-2022.2.18.dist-info/entry_points.txt
cwlformat-2022.2.18.dist-info/top_level.txt
cwlformat-2022.2.18.dist-info/RECORD
