Metadata-Version: 2.1
Name: cwlformat
Version: 2022.2.18
Summary: A prettifier for CWL code
Home-page: https://github.com/rabix/cwl-format
Author: Kaushik Ghose
Author-email: kaushik.ghose@sbgenomics.com
License: UNKNOWN
Platform: UNKNOWN
Requires-Python: >=3.6.0
Requires-Dist: ruamel.yaml (>=0.16.12)
Requires-Dist: importlib-resources ; python_version<"3.7"
